README.md
setup.py
varrr_3/__init__.py
varrr_3/see.py
varrr_3.egg-info/PKG-INFO
varrr_3.egg-info/SOURCES.txt
varrr_3.egg-info/dependency_links.txt
varrr_3.egg-info/requires.txt
varrr_3.egg-info/top_level.txt
varrr_3/theory/1.png
varrr_3/theory/123.pdf
varrr_3/theory/2.png
varrr_3/theory/3.png
varrr_3/theory/4.png
varrr_3/theory/__init__.py